MANIFEST.in
README.rst
setup.py
LunarSolarConverter/LunarSolarConverter.py
LunarSolarConverter/__init__.py
LunarSolarConverter/check.py
LunarSolarConverter/pypiDemo.py
LunarSolarConverter.egg-info/PKG-INFO
LunarSolarConverter.egg-info/SOURCES.txt
LunarSolarConverter.egg-info/dependency_links.txt
LunarSolarConverter.egg-info/entry_points.txt
LunarSolarConverter.egg-info/top_level.txt
LunarSolarConverter.egg-info/zip-safe