Metadata-Version: 1.0
Name: LunarSolarConverter
Version: 1.1.0
Summary: a lunar-solar converter
Home-page: https://github.com/isee15/Lunar-Solar-Calendar-Converter
Author: isee15
Author-email: isee15@outlook.com
License: MIT
Keywords: python lunar solar converter
Platform: UNKNOWN
